fp4nt/__init__.py
fp4nt/file_parser.py
fp4nt-1.1.2.dist-info/LICENSE
fp4nt-1.1.2.dist-info/METADATA
fp4nt-1.1.2.dist-info/WHEEL
fp4nt-1.1.2.dist-info/top_level.txt
fp4nt-1.1.2.dist-info/RECORD
