Metadata-Version: 2.1
Name: fp4nt
Version: 1.1.2
Summary: Fp4NT is a file parsing tool specially designed for processing and converting nested tabular data. It supports multiple input formats, such as HTML and Excel, and converts them to Markdown-formatted tables.
Home-page: https://github.com/charlie3go/fp4nt
Author: charlie3go
Author-email: aslongrushan@gmail.com
Classifier: Programming Language :: Python :: 3
Classifier: License :: OSI Approved :: MIT License
Classifier: Operating System :: OS Independent
Requires-Python: >=3.7
License-File: LICENSE
Requires-Dist: beautifulsoup4 >=4.9.0
Requires-Dist: html2text >=2020.1.16
Requires-Dist: pandas >=1.0.0
Requires-Dist: openpyxl >=3.0.0
